dualported_ram.v
`timescale 1ns / 1ps
module dualported_ram(
	input clk,
	input [12:0] addr0,
	input [12:0] addr1,
	input cs0,
	input cs1,
	input oe,
	input [3:0] we,
	output [63:0] data0,
	output [31:0] data1_o,
	input [31:0] data1_i
);

reg [7:0] flash [0:8191];

initial	$readmemh("a.hex", flash);

always @(posedge clk) begin
	if (we[3])
		flash[addr1+3] <= data1_i[31:24];
	if (we[2])
		flash[addr1+2] <= data1_i[23:16];
	if (we[1])
		flash[addr1+1] <= data1_i[15:8];
	if (we[0])
		flash[addr1] <= data1_i[7:0];
end

assign data0 = ~cs0 ? 64'bz : {flash[addr0+3], flash[addr0+2], flash[addr0+1], flash[addr0], flash[addr0+7], flash[addr0+6], flash[addr0+5], flash[addr0+4]};
assign data1_o = ~oe | ~cs1 ? 32'bz : {flash[addr1+3], flash[addr1+2], flash[addr1+1], flash[addr1]};

endmodule

riscv_writeback.v
`timescale 1ns / 1ps

module riscv_writeback(
	/* verilator lint_off UNUSED */
	input [31:0] opcode,
	/* verilator lint_on UNUSED */
	input [31:0] alu_result,
	input [31:0] adder_result,
	input lword,
	input lhalfword,
	input [31:0] ld_data,

	output [31:0] rd
);

assign rd	=	opcode[13] | opcode[5] | opcode[25] | opcode[27] ?	adder_result :
				opcode[4] | opcode[12]	? alu_result :
				opcode[0]				?  (lword ? ld_data :
											lhalfword ? {16'b0,ld_data[15:0]} :
											{24'b0,ld_data[7:0]}) :
				32'b0;

endmodule

riscv_memaccess.v
`timescale 1ns / 1ps

module riscv_memaccess (
	input	is_st,
	input	is_ld,
	input	[2:0] funct3,
	input	[31:0] rs2,
	input	[31:0] adder_result,
	
	output	[31:0] st_data,
	output	[3:0] st_mask,
	output	[31:0] addr
);

assign st_data	=	is_st ? (	funct3[0] ? {24'bz, rs2[7:0]} :
								funct3[1] ? {16'bz, rs2[15:0]} :
								funct3[2] ? rs2 :
								32'bz ) :
					32'bz;

assign st_mask	=	is_st | is_ld ? (	funct3[0] ? 4'b1 :
								funct3[1] ? 4'b11 :
								funct3[2] ? 4'b1111 :
								4'bz ) :
					4'bz;

assign addr		=	is_st | is_ld ? adder_result :
					32'bz;

endmodule

riscv_alu.v
`timescale 1ns / 1ps

module riscv_alu(
	input	[31:0] PC,

	input	[31:0] i_imm,
	input	[31:0] s_imm,
	input	[31:0] u_imm,

	input	funct7,

	input	[31:0] rs2,
	input	[31:0] rs1,
	
	input	[7:0] funct3,

	/* verilator lint_off UNUSED */
	input	[31:0] opcode,
	/* verilator lint_on UNUSED */

	output	[31:0] adder,
	output	[31:0] result,
	output	branch_taken
);

wire lt;
wire eq;
wire ltu;

wire [31:0] in1 =	opcode[25] | opcode[27] | opcode[5] ? PC :
					opcode[13] ? 0 :
					rs1;

wire [31:0] in2	=	opcode[12] | opcode[24] ? rs2 :
					opcode[8] ? s_imm :
					opcode[5] | opcode[13] ? u_imm :
					opcode[25] | opcode[27] ? 4 :
					i_imm;

assign adder		= in1 + in2;
wire [32:0] subber	= {1'b1, ~in2} + {1'b0, in1} + 33'b1;

assign lt		= 	(in1[31] & in2[31]) ? in1[31] :
				subber[32];
				
assign ltu	=	subber[32];
assign eq		=	(subber[31:0] == 0);

assign result	=	(funct3[0] ? (funct7 & opcode[12]) ? subber[31:0] : adder		: 32'b0) |
					(funct3[1] ? in1 << in2[4:0]									: 32'b0) |
					(funct3[2] ? {31'b0, lt}										: 32'b0) |
					(funct3[3] ? {31'b0, ltu}										: 32'b0) |
					(funct3[4] ? in1 ^ in2											: 32'b0) |
					(funct3[5] ? funct7 ? in1 >>> in2[4:0] : in1 >> in2[4:0]		: 32'b0) |
					(funct3[6] ? in1 | in2											: 32'b0) |
					(funct3[7] ? in1 & in2											: 32'b0) ;

assign branch_taken =	opcode[24] & (	(funct3[0] & eq) |
										(funct3[1] & ~eq) |
										(funct3[4] & lt) |
										(funct3[5] & ~lt) |
										(funct3[6] & ltu) |
										(funct3[7] & ~ltu) );
endmodule

riscv_decode.v
`timescale 1ns / 1ps

module riscv_decode (
	input	[31:0] instr,

	output	[31:0] uimm,
	output	[31:0] iimm,
	output	[31:0] simm,
	output	[31:0] bimm,
	output	[31:0] jimm,

	output	funct7,

	output	[11:0] csr,

	output	[4:0] rs2,
	output	[4:0] rs1,

	output	[7:0] funct3,

	output	[4:0] rd,

	output	[31:0] opcode,
	output	is_legal
);

assign uimm	= {instr[31], instr[30:12], 12'b0};
assign iimm	= {{21{instr[31]}}, instr[30:20]};
assign simm	= {{21{instr[31]}}, instr[30:25], instr[11:7]};
assign bimm	= {{20{instr[31]}}, instr[7], instr[30:25], instr[11:8], 1'b0};
assign jimm	= {{12{instr[31]}}, instr[19:12], instr[20], instr[30:21], 1'b0};

assign funct7	= instr[30];

assign csr		= instr[31:20];

assign rs2		= instr[24:20];
assign rs1		= instr[19:15];

assign funct3	= 8'h1 << instr[14:12];

assign rd		= instr[11:7];

assign opcode	= 32'h1 << instr[6:2];

assign is_legal	= instr[1] & instr[0];

endmodule

riscv.v
`timescale 1ns / 1ps

module riscv(
	input	clk_i,
	input	rst_i_b,

	output	[31:0] d_addr_o,
	input	[31:0] d_data_i,
	output	[31:0] d_data_o,
	output	[3:0] d_mask_o,

	output	[31:0] i_addr_o,
	input	[31:0] i_data_i,

	output	d_rdflag_o,
	
	input	d_membusy_i
);

initial begin
	$dumpfile("wave.vcd");
	$dumpvars(0, BitchRV32);
end

/*===================*/
/*    FETCH Stage    */
/*===================*/

reg [31:0] PC;

wire [31:0] nextpc =	~rst_i_b ? 0 :
						branch_taken ? PC + bimm :
						opcode[27] ? PC + jimm :
						opcode[25] ? INT[rs1] :
						PC + 4;

assign i_addr_o = PC;

always @(posedge clk_i)
	PC <= rst_i_b ? nextpc : 0;

/*====================*/
/*    DECODE Stage    */
/*====================*/

riscv_decode ID (
	i_data_i,

	uimm, iimm, simm, bimm, jimm,
	funct7,
	csr,
	rs2, rs1,
	funct3,
	rd,
	opcode,
	is_legal
);

wire [31:0] uimm;
wire [31:0] iimm;
wire [31:0] simm;
wire [31:0] bimm;
wire [31:0] jimm;

wire funct7;

wire [11:0] csr;

wire [4:0] rs2;
wire [4:0] rs1;

wire [7:0] funct3;

wire [4:0] rd;

wire [31:0] opcode;

wire is_legal;

wire [31:0] csr_ =	funct3[2] ? INT[rs1] | CSR[csr[2:0]] :
					funct3[3] ? ~INT[rs1] & CSR[csr[2:0]] :
					funct3[5] ? {27'b0, i_data_i[19:15]} :
					funct3[6] ? CSR[csr[2:0]] | {27'b0, i_data_i[19:15]} :
					funct3[7] ? {CSR[csr[2:0]][31:5], CSR[csr[2:0]][4:0] & ~i_data_i[19:15]} :
					INT[rs1];

/*=====================*/
/*    EXECUTE Stage    */
/*=====================*/

riscv_alu EX (
	PC,
	iimm,
	simm,
	uimm,
	funct7,
	INT[rs2],
	INT[rs1],
	funct3,
	opcode,

	adder_result,
	alu_result,
	branch_taken
);

wire [31:0] adder_result;
wire [31:0] alu_result;
wire branch_taken;

/*=======================*/
/*    MEMACCESS Stage    */
/*=======================*/

riscv_memaccess MEM (
	opcode[8],
	opcode[0],
	funct3[2:0],
	INT[rs2],
	adder_result,

	st_data,
	st_mask,
	dmem_addr
);

wire [31:0] st_data;
wire [3:0] st_mask;
wire [31:0] dmem_addr;

assign d_data_o = st_data;
assign d_mask_o = opcode[8] ? st_mask : 0;
assign d_addr_o = dmem_addr;
assign d_rdflag_o = opcode[0];

/*=======================*/
/*    WRITEBACK Stage    */
/*=======================*/

riscv_writeback WB (
	opcode,
	alu_result,
	adder_result,
	st_mask[3],
	st_mask[1],
	d_data_i,

	rd_
);

wire [31:0] rd_;

reg [31:0] INT [0:31];
reg [31:0] CSR [0:7];

always @(posedge clk_i) begin
	if (rd != 0 & ~opcode[8] & ~branch_taken)
		INT[rd] <= rd_;
	if (rd != 0 & opcode[28])
		INT[rd] <= CSR[csr[2:0]];
	if (csr[11:10] != 2'b11 & opcode[28])
		CSR[csr[2:0]] <= csr_;
end

endmodule

top.v
`timescale 1ns / 1ps
module top (
	input clk,
	input reset
);

wire [31:0] addr;
wire [31:0] rdata;
wire [31:0] wdata;
wire [3:0] wmask;

wire [31:0] i_addr;
wire [63:0] i_data;

wire rdflag;

wire i_cs = (i_addr[31:15] == 17'b00000000000000000);
wire cs = (addr[31:15] == 17'b00000000000000000);

wire membusy = 0;

riscv core0 (
	clk,
	reset,

	addr,
	rdata,
	wdata,
	wmask,

	i_addr,
	i_data[63:32],

	rdflag,

	membusy
);

dualported_ram imem (
	clk,
	i_addr[12:0],
	addr[12:0],
	i_cs,
	cs,
	rdflag,
	wmask,
	i_data,
	rdata,
	wdata
);

endmodule

obj_dir/wave.vcd
$version Generated by VerilatedVcd $end
$date Mon May 23 13:20:07 2022 $end
$timescale 1ps $end

 $scope module TOP $end
  $var wire  1 y clk $end
  $var wire  1 z reset $end
  $scope module top $end
   $var wire 32 # addr [31:0] $end
   $var wire  1 y clk $end
   $var wire  1 , cs $end
   $var wire 32 ' i_addr [31:0] $end
   $var wire  1 + i_cs $end
   $var wire 64 ( i_data [63:0] $end
   $var wire  1 | membusy $end
   $var wire 32 $ rdata [31:0] $end
   $var wire  1 * rdflag $end
   $var wire  1 z reset $end
   $var wire 32 % wdata [31:0] $end
   $var wire  4 & wmask [3:0] $end
   $scope module core0 $end
    $var wire 32 a CSR[0] [31:0] $end
    $var wire 32 b CSR[1] [31:0] $end
    $var wire 32 c CSR[2] [31:0] $end
    $var wire 32 d CSR[3] [31:0] $end
    $var wire 32 e CSR[4] [31:0] $end
    $var wire 32 f CSR[5] [31:0] $end
    $var wire 32 g CSR[6] [31:0] $end
    $var wire 32 h CSR[7] [31:0] $end
    $var wire 32 A INT[0] [31:0] $end
    $var wire 32 K INT[10] [31:0] $end
    $var wire 32 L INT[11] [31:0] $end
    $var wire 32 M INT[12] [31:0] $end
    $var wire 32 N INT[13] [31:0] $end
    $var wire 32 O INT[14] [31:0] $end
    $var wire 32 P INT[15] [31:0] $end
    $var wire 32 Q INT[16] [31:0] $end
    $var wire 32 R INT[17] [31:0] $end
    $var wire 32 S INT[18] [31:0] $end
    $var wire 32 T INT[19] [31:0] $end
    $var wire 32 B INT[1] [31:0] $end
    $var wire 32 U INT[20] [31:0] $end
    $var wire 32 V INT[21] [31:0] $end
    $var wire 32 W INT[22] [31:0] $end
    $var wire 32 X INT[23] [31:0] $end
    $var wire 32 Y INT[24] [31:0] $end
    $var wire 32 Z INT[25] [31:0] $end
    $var wire 32 [ INT[26] [31:0] $end
    $var wire 32 \ INT[27] [31:0] $end
    $var wire 32 ] INT[28] [31:0] $end
    $var wire 32 ^ INT[29] [31:0] $end
    $var wire 32 C INT[2] [31:0] $end
    $var wire 32 _ INT[30] [31:0] $end
    $var wire 32 ` INT[31] [31:0] $end
    $var wire 32 D INT[3] [31:0] $end
    $var wire 32 E INT[4] [31:0] $end
    $var wire 32 F INT[5] [31:0] $end
    $var wire 32 G INT[6] [31:0] $end
    $var wire 32 H INT[7] [31:0] $end
    $var wire 32 I INT[8] [31:0] $end
    $var wire 32 J INT[9] [31:0] $end
    $var wire 32 ' PC [31:0] $end
    $var wire 32 < adder_result [31:0] $end
    $var wire 32 = alu_result [31:0] $end
    $var wire 32 1 bimm [31:0] $end
    $var wire  1 > branch_taken $end
    $var wire  1 y clk_i $end
    $var wire 12 4 csr [11:0] $end
    $var wire 32 ; csr_ [31:0] $end
    $var wire 32 # d_addr_o [31:0] $end
    $var wire 32 $ d_data_i [31:0] $end
    $var wire 32 % d_data_o [31:0] $end
    $var wire  4 & d_mask_o [3:0] $end
    $var wire  1 | d_membusy_i $end
    $var wire  1 * d_rdflag_o $end
    $var wire 32 # dmem_addr [31:0] $end
    $var wire  8 7 funct3 [7:0] $end
    $var wire  1 3 funct7 $end
    $var wire 32 ' i_addr_o [31:0] $end
    $var wire 32 - i_data_i [31:0] $end
    $var wire 32 / iimm [31:0] $end
    $var wire  1 : is_legal $end
    $var wire 32 2 jimm [31:0] $end
    $var wire 32 { nextpc [31:0] $end
    $var wire 32 9 opcode [31:0] $end
    $var wire  5 8 rd [4:0] $end
    $var wire 32 @ rd_ [31:0] $end
    $var wire  5 6 rs1 [4:0] $end
    $var wire  5 5 rs2 [4:0] $end
    $var wire  1 z rst_i_b $end
    $var wire 32 0 simm [31:0] $end
    $var wire 32 % st_data [31:0] $end
    $var wire  4 ? st_mask [3:0] $end
    $var wire 32 . uimm [31:0] $end
    $scope module EX $end
     $var wire 32 ' PC [31:0] $end
     $var wire 32 < adder [31:0] $end
     $var wire  1 > branch_taken $end
     $var wire  1 l eq $end
     $var wire  8 7 funct3 [7:0] $end
     $var wire  1 3 funct7 $end
     $var wire 32 / i_imm [31:0] $end
     $var wire 32 n in1 [31:0] $end
     $var wire 32 o in2 [31:0] $end
     $var wire  1 k lt $end
     $var wire  1 m ltu $end
     $var wire 32 9 opcode [31:0] $end
     $var wire 32 = result [31:0] $end
     $var wire 32 j rs1 [31:0] $end
     $var wire 32 i rs2 [31:0] $end
     $var wire 32 0 s_imm [31:0] $end
     $var wire 33 p subber [32:0] $end
     $var wire 32 . u_imm [31:0] $end
    $upscope $end
    $scope module ID $end
     $var wire 32 1 bimm [31:0] $end
     $var wire 12 4 csr [11:0] $end
     $var wire  8 7 funct3 [7:0] $end
     $var wire  1 3 funct7 $end
     $var wire 32 / iimm [31:0] $end
     $var wire 32 - instr [31:0] $end
     $var wire  1 : is_legal $end
     $var wire 32 2 jimm [31:0] $end
     $var wire 32 9 opcode [31:0] $end
     $var wire  5 8 rd [4:0] $end
     $var wire  5 6 rs1 [4:0] $end
     $var wire  5 5 rs2 [4:0] $end
     $var wire 32 0 simm [31:0] $end
     $var wire 32 . uimm [31:0] $end
    $upscope $end
    $scope module MEM $end
     $var wire 32 < adder_result [31:0] $end
     $var wire 32 # addr [31:0] $end
     $var wire  3 s funct3 [2:0] $end
     $var wire  1 * is_ld $end
     $var wire  1 r is_st $end
     $var wire 32 t rs2 [31:0] $end
     $var wire 32 % st_data [31:0] $end
     $var wire  4 ? st_mask [3:0] $end
    $upscope $end
    $scope module WB $end
     $var wire 32 < adder_result [31:0] $end
     $var wire 32 = alu_result [31:0] $end
     $var wire 32 $ ld_data [31:0] $end
     $var wire  1 v lhalfword $end
     $var wire  1 u lword $end
     $var wire 32 9 opcode [31:0] $end
     $var wire 32 @ rd [31:0] $end
    $upscope $end
   $upscope $end
   $scope module imem $end
    $var wire 13 w addr0 [12:0] $end
    $var wire 13 x addr1 [12:0] $end
    $var wire  1 y clk $end
    $var wire  1 + cs0 $end
    $var wire  1 , cs1 $end
    $var wire 64 ( data0 [63:0] $end
    $var wire 32 % data1_i [31:0] $end
    $var wire 32 $ data1_o [31:0] $end
    $var wire  1 * oe $end
    $var wire  4 & we [3:0] $end
   $upscope $end
  $upscope $end
 $upscope $end
$enddefinitions $end


#1
b00000000000000000000000000000000 #
b00000000000000000000000000000000 $
b00000000000000000000000000000000 %
b0000 &
b00000000000000000000000000000000 '
b0000000000000000000000000001001100001111111100000000010000010011 (
0*
1+
1,
b00000000000000000000000000010011 -
b00000000000000000000000000000000 .
b00000000000000000000000000000000 /
b00000000000000000000000000000000 0
b00000000000000000000000000000000 1
b00000000000000000000000000000000 2
03
b000000000000 4
b00000 5
b00000 6
b00000001 7
b00000 8
b00000000000000000000000000010000 9
1:
b00000000000000000000000000000000 ;
b00000000000000000000000000000000 <
b00000000000000000000000000000000 =
0>
b0000 ?
b00000000000000000000000000000000 @
b00000000000000000000000000000000 A
b00000000000000000000000000000000 B
b00000000000000000000000000000000 C
b00000000000000000000000000000000 D
b00000000000000000000000000000000 E
b00000000000000000000000000000000 F
b00000000000000000000000000000000 G
b00000000000000000000000000000000 H
b00000000000000000000000000000000 I
b00000000000000000000000000000000 J
b00000000000000000000000000000000 K
b00000000000000000000000000000000 L
b00000000000000000000000000000000 M
b00000000000000000000000000000000 N
b00000000000000000000000000000000 O
b00000000000000000000000000000000 P
b00000000000000000000000000000000 Q
b00000000000000000000000000000000 R
b00000000000000000000000000000000 S
b00000000000000000000000000000000 T
b00000000000000000000000000000000 U
b00000000000000000000000000000000 V
b00000000000000000000000000000000 W
b00000000000000000000000000000000 X
b00000000000000000000000000000000 Y
b00000000000000000000000000000000 Z
b00000000000000000000000000000000 [
b00000000000000000000000000000000 \
b00000000000000000000000000000000 ]
b00000000000000000000000000000000 ^
b00000000000000000000000000000000 _
b00000000000000000000000000000000 `
b00000000000000000000000000000000 a
b00000000000000000000000000000000 b
b00000000000000000000000000000000 c
b00000000000000000000000000000000 d
b00000000000000000000000000000000 e
b00000000000000000000000000000000 f
b00000000000000000000000000000000 g
b00000000000000000000000000000000 h
b00000000000000000000000000000000 i
b00000000000000000000000000000000 j
0k
1l
0m
b00000000000000000000000000000000 n
b00000000000000000000000000000000 o
b000000000000000000000000000000000 p
0r
b001 s
b00000000000000000000000000000000 t
0u
0v
b0000000000000 w
b0000000000000 x
0y
0z
b00000000000000000000000000000000 {
0|
#2
#3
#4
#5
#6
#7
#8
#9
#10
1y
#11
#12
#13
#14
#15
#16
#17
#18
#19
#20
0y
#21
#22
#23
#24
#25
#26
#27
#28
#29
#30
1y
#31
#32
#33
#34
#35
#36
#37
#38
#39
#40
0y
#41
#42
#43
#44
#45
#46
#47
#48
#49
#50
1y
#51
#52
#53
#54
#55
#56
#57
#58
#59
#60
0y
#61
#62
#63
#64
#65
#66
#67
#68
#69
#70
1y
#71
#72
#73
#74
#75
#76
#77
#78
#79
#80
0y
#81
#82
#83
#84
#85
#86
#87
#88
#89
#90
1y
#91
#92
#93
#94
#95
#96
#97
#98
#99
#100
0y
1z
b00000000000000000000000000000100 {
#101
#102
#103
#104
#105
#106
#107
#108
#109
#110
b00000000000000000000000000000100 '
b0000111111110000000001000001001111111111000000000000010100110111 (
b00001111111100000000010000010011 -
b00001111111100000000000000000000 .
b00000000000000000000000011111111 /
b00000000000000000000000011101000 0
b00000000000000000000000011101000 1
b00000000000000000000100011111110 2
b000011111111 4
b11111 5
b01000 8
b00000000000000000000000011111111 <
b00000000000000000000000011111111 =
b00000000000000000000000011111111 @
1k
0l
1m
b00000000000000000000000011111111 o
b111111111111111111111111100000001 p
b0000000000100 w
1y
b00000000000000000000000000001000 {
#111
#112
#113
#114
#115
#116
#117
#118
#119
#120
0y
#121
#122
#123
#124
#125
#126
#127
#128
#129
#130
b00000000000000000000000000001000 '
b1111111100000000000001010011011110110000000001000001000001110011 (
b11111111000000000000010100110111 -
b11111111000000000000000000000000 .
b11111111111111111111111111110000 /
b11111111111111111111111111101010 0
b11111111111111111111011111101010 1
b11111111111100000000011111110000 2
13
b111111110000 4
b10000 5
b01010 8
b00000000000000000010000000000000 9
b11111111000000000000000000000000 <
b11111111000000000000000000000000 =
b11111111000000000000000000000000 @
b00000000000000000000000011111111 I
b11111111000000000000000000000000 o
b100000001000000000000000000000000 p
b0000000001000 w
1y
b00000000000000000000000000001100 {
#131
#132
#133
#134
#135
#136
#137
#138
#139
#140
0y
#141
#142
#143
#144
#145
#146
#147
#148
#149
#150
b00000000000000000000000000001100 '
b1011000000000100000100000111001110110000000001010010000001110011 (
b10110000000001000001000001110011 -
b10110000000001000001000000000000 .
b11111111111111111111101100000000 /
b11111111111111111111101100000000 0
b11111111111111111111001100000000 1
b11111111111101000001001100000000 2
03
b101100000000 4
b00000 5
b01000 6
b00000010 7
b00000 8
b00010000000000000000000000000000 9
b00000000000000000000000011111111 ;
b11111111111111111111101111111111 <
b00000000000000000000000011111111 =
b00000000000000000000000000000000 @
b11111111000000000000000000000000 K
b00000000000000000000000011111111 j
b00000000000000000000000011111111 n
b11111111111111111111101100000000 o
b100000000000000000000010111111111 p
b010 s
b0000000001100 w
1y
b00000000000000000000000000010000 {
#151
#152
#153
#154
#155
#156
#157
#158
#159
#160
0y
#161
#162
#163
#164
#165
#166
#167
#168
#169
#170
b00000000000000000000000000010000 '
b1011000000000101001000000111001110110000000000101111000001110011 (
b10110000000001010010000001110011 -
b10110000000001010010000000000000 .
b11111111111101010010001100000000 2
b01010 6
b00000100 7
b11111111000000000000000011111111 ;
b11111110111111111111101100000000 <
b00000000000000000000000000000001 =
b00000000000000000000000011111111 a
b11111111000000000000000000000000 j
b11111111000000000000000000000000 n
b111111111000000000000010100000000 p
b100 s
b0000000010000 w
1y
b00000000000000000000000000010100 {
#171
#172
#173
#174
#175
#176
#177
#178
#179
#180
0y
#181
#182
#183
#184
#185
#186
#187
#188
#189
#190
b00000000000000000000000000010100 '
b1011000000000010111100000111001100000000000000000000000001101111 (
b10110000000000101111000001110011 -
b10110000000000101111000000000000 .
b11111111111100101111001100000000 2
b00101 6
b10000000 7
b11111111000000000000000011111010 ;
b11111111111111111111101100000000 <
b00000000000000000000000000000000 =
b11111111000000000000000011111111 a
b00000000000000000000000000000000 j
b00000000000000000000000000000000 n
b100000000000000000000010100000000 p
b000 s
b0000000010100 w
1y
b00000000000000000000000000011000 {
#191
#192
#193
#194
#195
#196
#197
#198
#199
#200
0y
#201
#202
#203
#204
#205
#206
#207
#208
#209
#210
b00000000000000000000000000011000 '
b0000000000000000000000000110111100000000000000000000000000000000 (
b00000000000000000000000001101111 -
b00000000000000000000000000000000 .
b00000000000000000000000000000000 /
b00000000000000000000000000000000 0
b00000000000000000000000000000000 1
b00000000000000000000000000000000 2
b000000000000 4
b00000 6
b00000001 7
b00001000000000000000000000000000 9
b00000000000000000000000000000000 ;
b00000000000000000000000000011100 <
b00000000000000000000000000011100 =
b00000000000000000000000000011100 @
b11111111000000000000000011111010 a
0k
0m
b00000000000000000000000000011000 n
b00000000000000000000000000000100 o
b000000000000000000000000000010100 p
b001 s
b0000000011000 w
1y
